{
  "round1": [
    "5",
    "11",
    "23",
    "47",
    "95",
    "191",
    "383",
    "767",
    "1535",
    "3071"
  ],
  "round2": [
    "1",
    "4",
    "9",
    "16",
    "25",
    "36",
    "49",
    "64",
    "81",
    "100"
  ],
  "round3": [
    "3",
    "8",
    "18",
    "38",
    "78",
    "158",
    "318",
    "638",
    "1278",
    "2558"
  ],
  "round4": [
    "6",
    "11",
    "21",
    "36",
    "56",
    "81",
    "111",
    "146",
    "186",
    "231"
  ],
  "round5": [
    "2",
    "3",
    "5",
    "9",
    "17",
    "33",
    "65",
    "129",
    "257",
    "513"
  ]
}
